MANIFEST.in
README.rst
setup.cfg
setup.py
sentry_insights/__init__.py
sentry_insights/models.py
sentry_insights.egg-info/PKG-INFO
sentry_insights.egg-info/SOURCES.txt
sentry_insights.egg-info/dependency_links.txt
sentry_insights.egg-info/entry_points.txt
sentry_insights.egg-info/not-zip-safe
sentry_insights.egg-info/requires.txt
sentry_insights.egg-info/top_level.txt