Metadata-Version: 1.1
Name: sentry-insights
Version: 0.1.1
Summary: A Sentry extension which integrates with New Relic Insights.
Home-page: http://github.com/tinyclues/sentry-insights
Author: Boris Feld
Author-email: boris.feld@tinyclues.com
License: BSD
Platform: UNKNOWN
Classifier: Framework :: Django
Classifier: Intended Audience :: Developers
Classifier: Intended Audience :: System Administrators
Classifier: Operating System :: OS Independent
Classifier: Topic :: Software Development
